[
    {
        "image":"/static/Cover.jpg",
        "audio":"/static/ピルグリム.mp3",
        "song":"ピルグリム",
        "album":"starring ReoNa - ELZA",
        "singer":"神崎エルザ",
        "isLike":true
    },{
        "image":"/static/Cover.jpg",
        "audio":"/static/step,step.mp3",
        "song":"step, step",
        "album":"starring ReoNa - ELZA",
        "singer":"神崎エルザ",
        "isLike":false
    },{
        "image":"/static/Cover.jpg",
        "audio":"/static/Independence.mp3",
        "song":"Independence",
        "album":"starring ReoNa - ELZA",
        "singer":"神崎エルザ",
        "isLike":false
    }, {
        "image":"/static/Cover.jpg",
        "audio":"/static/Rea(s)oN.mp3",
        "song":"Rea(s)oN",
        "album":"starring ReoNa - ELZA",
        "singer":"神崎エルザ",
        "isLike":true
    }
]
